skytree/__init__.py
skytree/animated.py
skytree/boards.py
skytree/collidable.py
skytree/component.py
skytree/config.py
skytree/drawable.py
skytree/examples.py
skytree/game.py
skytree/helpers.py
skytree/key_commands.py
skytree/layers.py
skytree/positional.py
skytree/resource_manager.py
skytree/singleton.py
skytree/sprites.py
skytree/stage.py
skytree/tile_objects.py
skytree/tileset.py
skytree/timers.py
skytree/tools.py
skytree/updateable.py
skytree/user_interface.py
skytree/example_resources/SkyFont.ttf
skytree/example_resources/ball0.png
skytree/example_resources/ball1.png
skytree/example_resources/ball2.png
skytree/example_resources/ball_pop.png
skytree/example_resources/checkpoint.ogg
skytree/example_resources/demo_bg.png
skytree/example_resources/demo_bg2.png
skytree/example_resources/demo_bg_scr10.png
skytree/example_resources/demo_bg_smol.png
skytree/example_resources/demo_map'.png
skytree/example_resources/demo_map.png
skytree/example_resources/demo_map.txt
skytree/example_resources/demo_map_bg.txt
skytree/example_resources/demo_map_tiles.png
skytree/example_resources/demo_pung.txt
skytree/example_resources/demo_pung_raw.txt
skytree/example_resources/demo_scr1.txt
skytree/example_resources/demo_scr10.txt
skytree/example_resources/demo_scr10_bg.txt
skytree/example_resources/demo_scr10_raw.txt
skytree/example_resources/demo_scr11.txt
skytree/example_resources/demo_scr11_raw.txt
skytree/example_resources/demo_scr12.txt
skytree/example_resources/demo_scr12_raw.txt
skytree/example_resources/demo_scr13.txt
skytree/example_resources/demo_scr13_raw.txt
skytree/example_resources/demo_scr1_raw.txt
skytree/example_resources/demo_scr2.txt
skytree/example_resources/demo_scr2_raw.txt
skytree/example_resources/demo_scr3.txt
skytree/example_resources/demo_scr3_raw.txt
skytree/example_resources/demo_scr4.txt
skytree/example_resources/demo_scr4_raw.txt
skytree/example_resources/demo_scr5.txt
skytree/example_resources/demo_scr5_raw.txt
skytree/example_resources/demo_scr6.txt
skytree-0.2.1.dist-info/LICENSE
skytree-0.2.1.dist-info/METADATA
skytree-0.2.1.dist-info/WHEEL
skytree-0.2.1.dist-info/top_level.txt
skytree-0.2.1.dist-info/RECORD
