Metadata-Version: 2.1
Name: skytree
Version: 0.2.1
Summary: A 2D game framework for Python
Home-page: https://github.com/Arndok/Skytree
Author: Pablo Reyes de Rojas
Author-email: cushinho@gmail.com
License: CC BY-NC-SA 4.0
Classifier: Development Status :: 3 - Alpha
Classifier: Intended Audience :: Developers
Classifier: Intended Audience :: Education
Classifier: Programming Language :: Python :: 3.6
Classifier: Programming Language :: Python :: 3.11
Classifier: License :: Other/Proprietary License
Classifier: Operating System :: OS Independent
Classifier: Topic :: Software Development :: Libraries
Classifier: Topic :: Games/Entertainment
Requires-Python: >=3.6, <3.12
License-File: LICENSE
Requires-Dist: pygame==2.6
